LICENSE
py3status_http_monitor/__init__.py
py3status_http_monitor/http_monitor.py
py3status_http_monitor-0.1.4.dist-info/entry_points.txt
py3status_http_monitor-0.1.4.dist-info/LICENSE
py3status_http_monitor-0.1.4.dist-info/WHEEL
py3status_http_monitor-0.1.4.dist-info/METADATA
py3status_http_monitor-0.1.4.dist-info/RECORD
