Metadata-Version: 2.1
Name: py3status-http-monitor
Version: 0.1.4
Summary: py3status http monitor show the status of http endpoints
Home-page: https://github.com/mcgillij/py3status-http-monitor
License: MIT
Keywords: http,monitor,status,i3,py3status
Author: mcgillij
Author-email: mcgillivray.jason@gmail.com
Requires-Python: >=3.9,<4.0
Classifier: Environment :: X11 Applications
Classifier: Intended Audience :: End Users/Desktop
Classifier: License :: OSI Approved :: MIT License
Classifier: Operating System :: POSIX :: Linux
Classifier: Programming Language :: Python :: 3
Classifier: Programming Language :: Python :: 3.10
Classifier: Programming Language :: Python :: 3.9
Classifier: Topic :: Desktop Environment :: Window Managers
Classifier: Topic :: System :: Monitoring
Requires-Dist: py3status (>=3.34,<4.0)
Project-URL: Documentation, https://github.com/mcgillij/py3status-http-monitor
Project-URL: Repository, https://github.com/mcgillij/py3status-http-monitor
